FeishuBitableAPI/ADD_RECORDS_FROM_CSV.py
FeishuBitableAPI/BUILD_FIELD.py
FeishuBitableAPI/CHECK_FIELD_EXIST.py
FeishuBitableAPI/CHECK_FIELD_EXIST_SQL.py
FeishuBitableAPI/CONVERSION_FIELDS.py
FeishuBitableAPI/CREATE_FIELD.py
FeishuBitableAPI/CREATE_TABLE.py
FeishuBitableAPI/CREATE_TABLE_QUICK.py
FeishuBitableAPI/DELETE_FIELDS.py
FeishuBitableAPI/DELETE_FIELDS_DEFAULT.py
FeishuBitableAPI/DELETE_RECORD.py
FeishuBitableAPI/FeishuBitableAPI.py
FeishuBitableAPI/GET_APP_ACCESS_TOKEN.py
FeishuBitableAPI/GET_FIELD_INFO.py
FeishuBitableAPI/GET_INFO_FROM_URL.py
FeishuBitableAPI/GET_LOGIN_CODE.py
FeishuBitableAPI/GET_RECORD.py
FeishuBitableAPI/GET_RECORD_ID.py
FeishuBitableAPI/GET_TABLE_ID.py
FeishuBitableAPI/GET_TENANT_ACCESS_TOKEN.py
FeishuBitableAPI/GET_USER_ACCESS_TOKEN.py
FeishuBitableAPI/GET_VIEW_ID.py
FeishuBitableAPI/LIST_FIELDS.py
FeishuBitableAPI/LIST_RECORDS.py
FeishuBitableAPI/LIST_TABLES.py
FeishuBitableAPI/LIST_VIEWS.py
FeishuBitableAPI/REFRESH_USER_ACCESS_TOKEN.py
FeishuBitableAPI/UPDATE_FIELD.py
FeishuBitableAPI/UPDATE_RECORD.py
FeishuBitableAPI/WRITE_APP_ACCESS_TOKEN.py
FeishuBitableAPI/WRITE_FIELD_INFO.py
FeishuBitableAPI/WRITE_INFO_FROM_URL.py
FeishuBitableAPI/WRITE_LOGIN_CODE.py
FeishuBitableAPI/WRITE_RECORD_ID.py
FeishuBitableAPI/WRITE_TABLE_ID.py
FeishuBitableAPI/WRITE_TENANT_ACCESS_TOKEN.py
FeishuBitableAPI/WRITE_VIEW_ID.py
FeishuBitableAPI/__init__.py
FeishuBitableAPI/__main__.py
FeishuBitableAPI/setup.py
FeishuBitableAPI/test.py
FeishuBitableAPI-3.3.3.dist-info/LICENSE
FeishuBitableAPI-3.3.3.dist-info/METADATA
FeishuBitableAPI-3.3.3.dist-info/WHEEL
FeishuBitableAPI-3.3.3.dist-info/top_level.txt
FeishuBitableAPI-3.3.3.dist-info/RECORD
