Metadata-Version: 2.1
Name: FeishuBitableAPI
Version: 3.3.3
Summary: A Python API for Feishu Bitable
Home-page: https://github.com/BlueSkyXN/Feishu-Bitable-Python-API
Author: BlueSkyXN
Author-email: bluesky@000714.xyz
Classifier: Development Status :: 5 - Production/Stable
Classifier: Intended Audience :: Developers
Classifier: License :: OSI Approved :: GNU General Public License v3 (GPLv3)
Classifier: Programming Language :: Python :: 3.10
Classifier: Programming Language :: Python :: 3.11
License-File: LICENSE
Requires-Dist: requests
Requires-Dist: pandas
